data_butler.py
data_butler-0.0.9.dist-info/LICENSE.txt
data_butler-0.0.9.dist-info/METADATA
data_butler-0.0.9.dist-info/WHEEL
data_butler-0.0.9.dist-info/dependency_links.txt
data_butler-0.0.9.dist-info/top_level.txt
data_butler-0.0.9.dist-info/RECORD
