Metadata-Version: 2.1
Name: data-butler
Version: 0.0.9
Summary: A data cataloguing package
Home-page: https://github.com/DataButler/Data-Butler
Author: Rahul Madhu
Author-email: rahul.madhu93@gmail.com
License: UNKNOWN
Platform: UNKNOWN
Classifier: Programming Language :: Python :: 3
Classifier: License :: OSI Approved :: MIT License
Classifier: Operating System :: OS Independent
Requires-Python: >=3.6
Requires-Dist: geonamescache
Requires-Dist: pycountry
Requires-Dist: matplotlib
Requires-Dist: pandas
Requires-Dist: PrettyTable
